{"user_action": "Session details of the course", "Video_Id": "null", "email_id": "6ac533285d26800deb6f3fdb5c1ee6a30807b0433aa3dcd506e9898f", "timestamp": "2017-06-22 17:03:18", "@timestamp": "2017-06-22T17:03:22.301Z", "time": "17:03:22.30", "video_log": "false", "time_in_seconds": "null", "Course_Id": "3123", "Kenlist_Id": "null", "offset": 391618099, "date": "2017-06-22"}
{"user_action": "User on curriculum leaderboard pag", "Video_Id": "null", "email_id": "6ac533285d26800deb6f3fdb5c1ee6a30807b0433aa3dcd506e9898f", "timestamp": "2017-06-22 17:02:44", "@timestamp": "2017-06-22T17:02:44.848Z", "time": "17:02:44.84", "video_log": "false", "time_in_seconds": "null", "Course_Id": "null", "Kenlist_Id": "null", "offset": 391605873, "date": "2017-06-22"}
{"user_action": "details of the session", "Video_Id": "null", "email_id": "6ac533285d26800deb6f3fdb5c1ee6a30807b0433aa3dcd506e9898f", "timestamp": "2017-06-22 17:12:21", "@timestamp": "2017-06-22T17:12:23.032Z", "time": "17:12:23.03", "video_log": "false", "time_in_seconds": "null", "Course_Id": "null", "Kenlist_Id": "null", "offset": 391787651, "date": "2017-06-22"}
{"user_action": "phrase cloud for the video", "Video_Id": "eYeiUR8NDd0", "email_id": "6ac533285d26800deb6f3fdb5c1ee6a30807b0433aa3dcd506e9898f", "timestamp": "2017-06-22 17:12:32", "@timestamp": "2017-06-22T17:12:33.133Z", "time": "17:12:33.13", "video_log": "false", "time_in_seconds": "null", "Course_Id": "null", "Kenlist_Id": "null", "offset": 391792772, "date": "2017-06-22"}
{"user_action": "User is paused", "Video_Id": "eYeiUR8NDd0", "email_id": "6ac533285d26800deb6f3fdb5c1ee6a30807b0433aa3dcd506e9898f", "timestamp": "2017-06-22 17:13:36", "@timestamp": "2017-06-22T17:13:36.738Z", "time": "17:13:36.73", "video_log": "true", "time_in_seconds": "2086.26256283187", "Course_Id": "3123", "Kenlist_Id": "4366", "offset": 391819725, "date": "2017-06-22"}
{"user_action": "User is paused", "Video_Id": "fCjjLleIEnA", "email_id": "6ac533285d26800deb6f3fdb5c1ee6a30807b0433aa3dcd506e9898f", "timestamp": "2017-06-22 17:14:19", "@timestamp": "2017-06-22T17:14:21.184Z", "time": "17:14:21.18", "video_log": "true", "time_in_seconds": "863.365132", "Course_Id": "3123", "Kenlist_Id": "4366", "offset": 391839200, "date": "2017-06-22"}
{"user_action": "User is on content show page", "Video_Id": "null", "email_id": "6ac533285d26800deb6f3fdb5c1ee6a30807b0433aa3dcd506e9898f", "timestamp": "2017-06-22 17:14:44", "@timestamp": "2017-06-22T17:14:44.428Z", "time": "17:14:44.42", "video_log": "false", "time_in_seconds": "null", "Course_Id": "null", "Kenlist_Id": "4366", "offset": 391854394, "date": "2017-06-22"}
{"user_action": "Youtube video is buffering ", "Video_Id": "CaBeAX1MbOc", "email_id": "6ac533285d26800deb6f3fdb5c1ee6a30807b0433aa3dcd506e9898f", "timestamp": "2017-06-22 17:14:44", "@timestamp": "2017-06-22T17:14:45.428Z", "time": "17:14:45.42", "video_log": "true", "time_in_seconds": "0", "Course_Id": "3123", "Kenlist_Id": "4366", "offset": 391857113, "date": "2017-06-22"}
{"user_action": "User is on content show page", "Video_Id": "null", "email_id": "6ac533285d26800deb6f3fdb5c1ee6a30807b0433aa3dcd506e9898f", "timestamp": "2017-06-22 17:16:44", "@timestamp": "2017-06-22T17:16:45.591Z", "time": "17:16:45.59", "video_log": "false", "time_in_seconds": "null", "Course_Id": "null", "Kenlist_Id": "4366", "offset": 391919148, "date": "2017-06-22"}
{"user_action": "User is paused", "Video_Id": "p04cmakotoI", "email_id": "6ac533285d26800deb6f3fdb5c1ee6a30807b0433aa3dcd506e9898f", "timestamp": "2017-06-22 17:17:20", "@timestamp": "2017-06-22T17:17:21.926Z", "time": "17:17:21.92", "video_log": "true", "time_in_seconds": "1559.7738053097394", "Course_Id": "3123", "Kenlist_Id": "4366", "offset": 391948873, "date": "2017-06-22"}
{"user_action": "Youtube video is buffering ", "Video_Id": "p04cmakotoI", "email_id": "6ac533285d26800deb6f3fdb5c1ee6a30807b0433aa3dcd506e9898f", "timestamp": "2017-06-22 17:17:21", "@timestamp": "2017-06-22T17:17:21.926Z", "time": "17:17:21.92", "video_log": "true", "time_in_seconds": "1559.7738053097394", "Course_Id": "3123", "Kenlist_Id": "4366", "offset": 391949379, "date": "2017-06-22"}
{"user_action": "User is playing", "Video_Id": "p04cmakotoI", "email_id": "6ac533285d26800deb6f3fdb5c1ee6a30807b0433aa3dcd506e9898f", "timestamp": "2017-06-22 17:17:21", "@timestamp": "2017-06-22T17:17:21.926Z", "time": "17:17:21.92", "video_log": "true", "time_in_seconds": "1559.7811541659394", "Course_Id": "3123", "Kenlist_Id": "4366", "offset": 391949853, "date": "2017-06-22"}
{"user_action": "User is playing", "Video_Id": "nxCUg8hJBTk", "email_id": "6ac533285d26800deb6f3fdb5c1ee6a30807b0433aa3dcd506e9898f", "timestamp": "2017-06-22 17:17:40", "@timestamp": "2017-06-22T17:17:41.117Z", "time": "17:17:41.11", "video_log": "true", "time_in_seconds": "0.002682", "Course_Id": "3123", "Kenlist_Id": "4366", "offset": 391973108, "date": "2017-06-22"}
{"user_action": "User watched", "Video_Id": "p04cmakotoI", "email_id": "6ac533285d26800deb6f3fdb5c1ee6a30807b0433aa3dcd506e9898f", "timestamp": "2017-06-22 17:17:29", "@timestamp": "2017-06-22T17:17:30.021Z", "time": "17:17:30.02", "video_log": "true", "time_in_seconds": "null", "Course_Id": "3123", "Kenlist_Id": "4366", "offset": 391970341, "date": "2017-06-22"}
{"user_action": "User is on content show page", "Video_Id": "null", "email_id": "6ac533285d26800deb6f3fdb5c1ee6a30807b0433aa3dcd506e9898f", "timestamp": "2017-06-22 17:18:20", "@timestamp": "2017-06-22T17:18:21.494Z", "time": "17:18:21.49", "video_log": "false", "time_in_seconds": "null", "Course_Id": "null", "Kenlist_Id": "4366", "offset": 391996845, "date": "2017-06-22"}
{"user_action": "User is on content show page", "Video_Id": "null", "email_id": "6ac533285d26800deb6f3fdb5c1ee6a30807b0433aa3dcd506e9898f", "timestamp": "2017-06-22 17:18:22", "@timestamp": "2017-06-22T17:18:23.541Z", "time": "17:18:23.54", "video_log": "false", "time_in_seconds": "null", "Course_Id": "null", "Kenlist_Id": "4366", "offset": 391998482, "date": "2017-06-22"}
{"user_action": "Youtube video is buffering ", "Video_Id": "fji9kJS6Ebo", "email_id": "6ac533285d26800deb6f3fdb5c1ee6a30807b0433aa3dcd506e9898f", "timestamp": "2017-06-22 17:19:05", "@timestamp": "2017-06-22T17:19:05.912Z", "time": "17:19:05.91", "video_log": "true", "time_in_seconds": "0", "Course_Id": "3123", "Kenlist_Id": "4366", "offset": 392013692, "date": "2017-06-22"}
{"user_action": "User is paused", "Video_Id": "nxCUg8hJBTk", "email_id": "6ac533285d26800deb6f3fdb5c1ee6a30807b0433aa3dcd506e9898f", "timestamp": "2017-06-22 17:17:59", "@timestamp": "2017-06-22T17:18:01.306Z", "time": "17:18:01.30", "video_log": "true", "time_in_seconds": "980.6290265486701", "Course_Id": "3123", "Kenlist_Id": "4366", "offset": 391985456, "date": "2017-06-22"}
{"user_action": "User is playing", "Video_Id": "fji9kJS6Ebo", "email_id": "6ac533285d26800deb6f3fdb5c1ee6a30807b0433aa3dcd506e9898f", "timestamp": "2017-06-22 17:19:25", "@timestamp": "2017-06-22T17:19:25.097Z", "time": "17:19:25.09", "video_log": "true", "time_in_seconds": "2029.96769609346", "Course_Id": "3123", "Kenlist_Id": "4366", "offset": 392020295, "date": "2017-06-22"}
{"user_action": "User watched", "Video_Id": "toIcUJ-9JN0", "email_id": "6ac533285d26800deb6f3fdb5c1ee6a30807b0433aa3dcd506e9898f", "timestamp": "2017-06-22 17:20:43", "@timestamp": "2017-06-22T17:20:45.837Z", "time": "17:20:45.83", "video_log": "true", "time_in_seconds": "null", "Course_Id": "3123", "Kenlist_Id": "4366", "offset": 392067944, "date": "2017-06-22"}
{"user_action": "User is on content show page", "Video_Id": "null", "email_id": "6ac533285d26800deb6f3fdb5c1ee6a30807b0433aa3dcd506e9898f", "timestamp": "2017-06-22 17:23:02", "@timestamp": "2017-06-22T17:23:07.079Z", "time": "17:23:07.07", "video_log": "false", "time_in_seconds": "null", "Course_Id": "null", "Kenlist_Id": "4366", "offset": 392117590, "date": "2017-06-22"}
{"user_action": "User is paused", "Video_Id": "AGFIMwE-X3E", "email_id": "6ac533285d26800deb6f3fdb5c1ee6a30807b0433aa3dcd506e9898f", "timestamp": "2017-06-22 17:22:25", "@timestamp": "2017-06-22T17:22:28.772Z", "time": "17:22:28.77", "video_log": "true", "time_in_seconds": "561.761569911505", "Course_Id": "3123", "Kenlist_Id": "4366", "offset": 392103192, "date": "2017-06-22"}
{"user_action": "User is on content show page", "Video_Id": "null", "email_id": "6ac533285d26800deb6f3fdb5c1ee6a30807b0433aa3dcd506e9898f", "timestamp": "2017-06-22 17:22:30", "@timestamp": "2017-06-22T17:22:30.773Z", "time": "17:22:30.77", "video_log": "false", "time_in_seconds": "null", "Course_Id": "null", "Kenlist_Id": "4366", "offset": 392105940, "date": "2017-06-22"}
{"user_action": "phrase cloud for the video", "Video_Id": "0z2ov0sEWtk", "email_id": "6ac533285d26800deb6f3fdb5c1ee6a30807b0433aa3dcd506e9898f", "timestamp": "2017-06-22 17:22:32", "@timestamp": "2017-06-22T17:22:33.817Z", "time": "17:22:33.81", "video_log": "false", "time_in_seconds": "null", "Course_Id": "null", "Kenlist_Id": "null", "offset": 392106873, "date": "2017-06-22"}
{"user_action": "phrase cloud for the video", "Video_Id": "AGFIMwE-X3E", "email_id": "6ac533285d26800deb6f3fdb5c1ee6a30807b0433aa3dcd506e9898f", "timestamp": "2017-06-22 17:22:03", "@timestamp": "2017-06-22T17:22:03.551Z", "time": "17:22:03.55", "video_log": "false", "time_in_seconds": "null", "Course_Id": "null", "Kenlist_Id": "null", "offset": 392099090, "date": "2017-06-22"}
{"user_action": "Youtube video is buffering ", "Video_Id": "AGFIMwE-X3E", "email_id": "6ac533285d26800deb6f3fdb5c1ee6a30807b0433aa3dcd506e9898f", "timestamp": "2017-06-22 17:22:03", "@timestamp": "2017-06-22T17:22:04.551Z", "time": "17:22:04.55", "video_log": "true", "time_in_seconds": "0", "Course_Id": "3123", "Kenlist_Id": "4366", "offset": 392099562, "date": "2017-06-22"}
{"user_action": "User is on content show page", "Video_Id": "null", "email_id": "6ac533285d26800deb6f3fdb5c1ee6a30807b0433aa3dcd506e9898f", "timestamp": "2017-06-22 17:22:02", "@timestamp": "2017-06-22T17:22:02.551Z", "time": "17:22:02.55", "video_log": "false", "time_in_seconds": "null", "Course_Id": "null", "Kenlist_Id": "4366", "offset": 392098192, "date": "2017-06-22"}
{"user_action": "Youtube video is buffering ", "Video_Id": "Z1c9qxQTv6Q", "email_id": "6ac533285d26800deb6f3fdb5c1ee6a30807b0433aa3dcd506e9898f", "timestamp": "2017-06-22 17:24:24", "@timestamp": "2017-06-22T17:24:25.769Z", "time": "17:24:25.76", "video_log": "true", "time_in_seconds": "0", "Course_Id": "3123", "Kenlist_Id": "4366", "offset": 392157914, "date": "2017-06-22"}
{"user_action": "User is playing", "Video_Id": "Z1c9qxQTv6Q", "email_id": "6ac533285d26800deb6f3fdb5c1ee6a30807b0433aa3dcd506e9898f", "timestamp": "2017-06-22 17:24:26", "@timestamp": "2017-06-22T17:24:26.769Z", "time": "17:24:26.76", "video_log": "true", "time_in_seconds": "0.0010001659393310547", "Course_Id": "3123", "Kenlist_Id": "4366", "offset": 392160276, "date": "2017-06-22"}
{"user_action": "Youtube video is buffering ", "Video_Id": "UqI_T-FBvgM", "email_id": "6ac533285d26800deb6f3fdb5c1ee6a30807b0433aa3dcd506e9898f", "timestamp": "2017-06-22 17:31:50", "@timestamp": "2017-06-22T17:31:52.372Z", "time": "17:31:52.37", "video_log": "true", "time_in_seconds": "707.1566973451321", "Course_Id": "3123", "Kenlist_Id": "4366", "offset": 392329646, "date": "2017-06-22"}
{"user_action": "User is paused", "Video_Id": "UqI_T-FBvgM", "email_id": "6ac533285d26800deb6f3fdb5c1ee6a30807b0433aa3dcd506e9898f", "timestamp": "2017-06-22 17:31:50", "@timestamp": "2017-06-22T17:31:52.372Z", "time": "17:31:52.37", "video_log": "true", "time_in_seconds": "707.1566973451321", "Course_Id": "3123", "Kenlist_Id": "4366", "offset": 392330588, "date": "2017-06-22"}
{"user_action": "User is playing", "Video_Id": "xHboEH7GKjM", "email_id": "6ac533285d26800deb6f3fdb5c1ee6a30807b0433aa3dcd506e9898f", "timestamp": "2017-06-22 17:32:53", "@timestamp": "2017-06-22T17:32:53.816Z", "time": "17:32:53.81", "video_log": "true", "time_in_seconds": "0.003925927520751953", "Course_Id": "3123", "Kenlist_Id": "4366", "offset": 392358897, "date": "2017-06-22"}
{"user_action": "Youtube video is buffering ", "Video_Id": "xHboEH7GKjM", "email_id": "6ac533285d26800deb6f3fdb5c1ee6a30807b0433aa3dcd506e9898f", "timestamp": "2017-06-22 17:35:15", "@timestamp": "2017-06-22T17:35:16.841Z", "time": "17:35:16.84", "video_log": "true", "time_in_seconds": "928.7241699115021", "Course_Id": "3123", "Kenlist_Id": "4366", "offset": 392423112, "date": "2017-06-22"}
{"user_action": "Youtube video is buffering ", "Video_Id": "tQxBIE5iKCM", "email_id": "6ac533285d26800deb6f3fdb5c1ee6a30807b0433aa3dcd506e9898f", "timestamp": "2017-06-22 17:36:14", "@timestamp": "2017-06-22T17:36:14.284Z", "time": "17:36:14.28", "video_log": "true", "time_in_seconds": "0", "Course_Id": "3123", "Kenlist_Id": "4366", "offset": 392444026, "date": "2017-06-22"}
{"user_action": "Course details", "Video_Id": "null", "email_id": "6ac533285d26800deb6f3fdb5c1ee6a30807b0433aa3dcd506e9898f", "timestamp": "2017-06-21 05:48:14", "@timestamp": "2017-06-21T05:48:14.927Z", "time": "05:48:14.92", "video_log": "false", "time_in_seconds": "null", "Course_Id": "3142", "Kenlist_Id": "null", "offset": 345480982, "date": "2017-06-21"}
{"user_action": "Session details of the course", "Video_Id": "null", "email_id": "6ac533285d26800deb6f3fdb5c1ee6a30807b0433aa3dcd506e9898f", "timestamp": "2017-06-21 05:48:14", "@timestamp": "2017-06-21T05:48:14.927Z", "time": "05:48:14.92", "video_log": "false", "time_in_seconds": "null", "Course_Id": "3142", "Kenlist_Id": "null", "offset": 345481408, "date": "2017-06-21"}
{"user_action": "Course details", "Video_Id": "null", "email_id": "6ac533285d26800deb6f3fdb5c1ee6a30807b0433aa3dcd506e9898f", "timestamp": "2017-06-21 05:48:09", "@timestamp": "2017-06-21T05:48:09.922Z", "time": "05:48:09.92", "video_log": "false", "time_in_seconds": "null", "Course_Id": "3136", "Kenlist_Id": "null", "offset": 345472026, "date": "2017-06-21"}
{"user_action": "On course show page", "Video_Id": "null", "email_id": "6ac533285d26800deb6f3fdb5c1ee6a30807b0433aa3dcd506e9898f", "timestamp": "2017-06-21 05:48:09", "@timestamp": "2017-06-21T05:48:09.922Z", "time": "05:48:09.92", "video_log": "false", "time_in_seconds": "null", "Course_Id": "null", "Kenlist_Id": "null", "offset": 345473741, "date": "2017-06-21"}
{"user_action": "On course show page", "Video_Id": "null", "email_id": "6ac533285d26800deb6f3fdb5c1ee6a30807b0433aa3dcd506e9898f", "timestamp": "2017-06-21 05:48:51", "@timestamp": "2017-06-21T05:48:51.955Z", "time": "05:48:51.95", "video_log": "false", "time_in_seconds": "null", "Course_Id": "null", "Kenlist_Id": "null", "offset": 345544029, "date": "2017-06-21"}
{"user_action": "Assignments of the sessions", "Video_Id": "null", "email_id": "6ac533285d26800deb6f3fdb5c1ee6a30807b0433aa3dcd506e9898f", "timestamp": "2017-06-21 05:49:02", "@timestamp": "2017-06-21T05:49:02.963Z", "time": "05:49:02.96", "video_log": "false", "time_in_seconds": "null", "Course_Id": "null", "Kenlist_Id": "null", "offset": 345560805, "date": "2017-06-21"}
{"user_action": "phrase cloud for the video", "Video_Id": "m790cqOnN9o", "email_id": "6ac533285d26800deb6f3fdb5c1ee6a30807b0433aa3dcd506e9898f", "timestamp": "2017-06-21 05:49:53", "@timestamp": "2017-06-21T05:49:54.000Z", "time": "05:49:54.00", "video_log": "false", "time_in_seconds": "null", "Course_Id": "null", "Kenlist_Id": "null", "offset": 345622723, "date": "2017-06-21"}
{"user_action": "User is on content show page", "Video_Id": "null", "email_id": "6ac533285d26800deb6f3fdb5c1ee6a30807b0433aa3dcd506e9898f", "timestamp": "2017-06-21 05:49:47", "@timestamp": "2017-06-21T05:49:47.996Z", "time": "05:49:47.99", "video_log": "false", "time_in_seconds": "null", "Course_Id": "null", "Kenlist_Id": "4288", "offset": 345610268, "date": "2017-06-21"}
{"user_action": "User is on content show page", "Video_Id": "null", "email_id": "6ac533285d26800deb6f3fdb5c1ee6a30807b0433aa3dcd506e9898f", "timestamp": "2017-06-21 05:49:49", "@timestamp": "2017-06-21T05:49:49.999Z", "time": "05:49:49.99", "video_log": "false", "time_in_seconds": "null", "Course_Id": "null", "Kenlist_Id": "4288", "offset": 345614506, "date": "2017-06-21"}
{"user_action": "phrase cloud for the video", "Video_Id": "m790cqOnN9o", "email_id": "6ac533285d26800deb6f3fdb5c1ee6a30807b0433aa3dcd506e9898f", "timestamp": "2017-06-21 05:49:50", "@timestamp": "2017-06-21T05:49:50.999Z", "time": "05:49:50.99", "video_log": "false", "time_in_seconds": "null", "Course_Id": "null", "Kenlist_Id": "null", "offset": 345615854, "date": "2017-06-21"}
{"user_action": "User is on content show page", "Video_Id": "null", "email_id": "6ac533285d26800deb6f3fdb5c1ee6a30807b0433aa3dcd506e9898f", "timestamp": "2017-06-21 05:49:51", "@timestamp": "2017-06-21T05:49:51.999Z", "time": "05:49:51.99", "video_log": "false", "time_in_seconds": "null", "Course_Id": "null", "Kenlist_Id": "4288", "offset": 345616552, "date": "2017-06-21"}
{"user_action": "phrase cloud for the video", "Video_Id": "m790cqOnN9o", "email_id": "6ac533285d26800deb6f3fdb5c1ee6a30807b0433aa3dcd506e9898f", "timestamp": "2017-06-21 05:50:03", "@timestamp": "2017-06-21T05:50:04.006Z", "time": "05:50:04.00", "video_log": "false", "time_in_seconds": "null", "Course_Id": "null", "Kenlist_Id": "null", "offset": 345650871, "date": "2017-06-21"}
{"user_action": "User is on content show page", "Video_Id": "null", "email_id": "6ac533285d26800deb6f3fdb5c1ee6a30807b0433aa3dcd506e9898f", "timestamp": "2017-06-21 05:49:57", "@timestamp": "2017-06-21T05:49:58.003Z", "time": "05:49:58.00", "video_log": "false", "time_in_seconds": "null", "Course_Id": "null", "Kenlist_Id": "4288", "offset": 345638870, "date": "2017-06-21"}
{"user_action": "User is on content show page", "Video_Id": "null", "email_id": "6ac533285d26800deb6f3fdb5c1ee6a30807b0433aa3dcd506e9898f", "timestamp": "2017-06-21 05:50:01", "@timestamp": "2017-06-21T05:50:02.006Z", "time": "05:50:02.00", "video_log": "false", "time_in_seconds": "null", "Course_Id": "null", "Kenlist_Id": "4288", "offset": 345648625, "date": "2017-06-21"}
{"user_action": "User is on content show page", "Video_Id": "null", "email_id": "6ac533285d26800deb6f3fdb5c1ee6a30807b0433aa3dcd506e9898f", "timestamp": "2017-06-21 05:49:44", "@timestamp": "2017-06-21T05:49:44.995Z", "time": "05:49:44.99", "video_log": "false", "time_in_seconds": "null", "Course_Id": "null", "Kenlist_Id": "4288", "offset": 345607166, "date": "2017-06-21"}
{"user_action": "User is on content show page", "Video_Id": "null", "email_id": "6ac533285d26800deb6f3fdb5c1ee6a30807b0433aa3dcd506e9898f", "timestamp": "2017-06-21 05:49:44", "@timestamp": "2017-06-21T05:49:44.995Z", "time": "05:49:44.99", "video_log": "false", "time_in_seconds": "null", "Course_Id": "null", "Kenlist_Id": "4288", "offset": 345607868, "date": "2017-06-21"}
{"user_action": "User is on content show page", "Video_Id": "null", "email_id": "6ac533285d26800deb6f3fdb5c1ee6a30807b0433aa3dcd506e9898f", "timestamp": "2017-06-21 05:49:45", "@timestamp": "2017-06-21T05:49:45.995Z", "time": "05:49:45.99", "video_log": "false", "time_in_seconds": "null", "Course_Id": "null", "Kenlist_Id": "4288", "offset": 345608608, "date": "2017-06-21"}
{"user_action": "Discussions of the course", "Video_Id": "null", "email_id": "6ac533285d26800deb6f3fdb5c1ee6a30807b0433aa3dcd506e9898f", "timestamp": "2017-06-21 05:50:28", "@timestamp": "2017-06-21T05:50:29.022Z", "time": "05:50:29.02", "video_log": "false", "time_in_seconds": "null", "Course_Id": "3136", "Kenlist_Id": "null", "offset": 345668516, "date": "2017-06-21"}
{"user_action": "User is playing", "Video_Id": "oXBvSYS0CLE", "email_id": "6ac533285d26800deb6f3fdb5c1ee6a30807b0433aa3dcd506e9898f", "timestamp": "2017-06-21 05:50:47", "@timestamp": "2017-06-21T05:50:48.033Z", "time": "05:50:48.03", "video_log": "true", "time_in_seconds": "0.0019998550415039062", "Course_Id": "3136", "Kenlist_Id": "4288", "offset": 345677881, "date": "2017-06-21"}
{"user_action": "Discussions of the sessions", "Video_Id": "null", "email_id": "6ac533285d26800deb6f3fdb5c1ee6a30807b0433aa3dcd506e9898f", "timestamp": "2017-06-21 05:50:34", "@timestamp": "2017-06-21T05:50:38.027Z", "time": "05:50:38.02", "video_log": "false", "time_in_seconds": "null", "Course_Id": "null", "Kenlist_Id": "null", "offset": 345671479, "date": "2017-06-21"}
{"user_action": "Discussions of the sessions", "Video_Id": "null", "email_id": "6ac533285d26800deb6f3fdb5c1ee6a30807b0433aa3dcd506e9898f", "timestamp": "2017-06-21 05:50:43", "@timestamp": "2017-06-21T05:50:44.030Z", "time": "05:50:44.03", "video_log": "false", "time_in_seconds": "null", "Course_Id": "null", "Kenlist_Id": "null", "offset": 345675376, "date": "2017-06-21"}
{"user_action": "details of the session", "Video_Id": "null", "email_id": "6ac533285d26800deb6f3fdb5c1ee6a30807b0433aa3dcd506e9898f", "timestamp": "2017-06-21 05:50:43", "@timestamp": "2017-06-21T05:50:44.030Z", "time": "05:50:44.03", "video_log": "false", "time_in_seconds": "null", "Course_Id": "null", "Kenlist_Id": "null", "offset": 345675578, "date": "2017-06-21"}
{"user_action": "User is on content show page", "Video_Id": "null", "email_id": "6ac533285d26800deb6f3fdb5c1ee6a30807b0433aa3dcd506e9898f", "timestamp": "2017-06-21 05:50:57", "@timestamp": "2017-06-21T05:50:59.039Z", "time": "05:50:59.03", "video_log": "false", "time_in_seconds": "null", "Course_Id": "null", "Kenlist_Id": "4288", "offset": 345680567, "date": "2017-06-21"}
{"user_action": "User is on content show page", "Video_Id": "null", "email_id": "6ac533285d26800deb6f3fdb5c1ee6a30807b0433aa3dcd506e9898f", "timestamp": "2017-06-21 05:51:07", "@timestamp": "2017-06-21T05:51:09.045Z", "time": "05:51:09.04", "video_log": "false", "time_in_seconds": "null", "Course_Id": "null", "Kenlist_Id": "4288", "offset": 345685138, "date": "2017-06-21"}
{"user_action": "Youtube video is buffering ", "Video_Id": "m790cqOnN9o", "email_id": "6ac533285d26800deb6f3fdb5c1ee6a30807b0433aa3dcd506e9898f", "timestamp": "2017-06-21 05:51:09", "@timestamp": "2017-06-21T05:51:10.048Z", "time": "05:51:10.04", "video_log": "true", "time_in_seconds": "0", "Course_Id": "3136", "Kenlist_Id": "4288", "offset": 345686722, "date": "2017-06-21"}
{"user_action": "User is on content show page", "Video_Id": "null", "email_id": "6ac533285d26800deb6f3fdb5c1ee6a30807b0433aa3dcd506e9898f", "timestamp": "2017-06-21 05:51:02", "@timestamp": "2017-06-21T05:51:03.042Z", "time": "05:51:03.04", "video_log": "false", "time_in_seconds": "null", "Course_Id": "null", "Kenlist_Id": "4288", "offset": 345682850, "date": "2017-06-21"}
{"user_action": "User is on content show page", "Video_Id": "null", "email_id": "6ac533285d26800deb6f3fdb5c1ee6a30807b0433aa3dcd506e9898f", "timestamp": "2017-06-21 05:52:10", "@timestamp": "2017-06-21T05:52:11.079Z", "time": "05:52:11.07", "video_log": "false", "time_in_seconds": "null", "Course_Id": "null", "Kenlist_Id": "4288", "offset": 345708545, "date": "2017-06-21"}
{"user_action": "phrase cloud for the video", "Video_Id": "4lNeRGyYL-4", "email_id": "6ac533285d26800deb6f3fdb5c1ee6a30807b0433aa3dcd506e9898f", "timestamp": "2017-06-21 05:52:58", "@timestamp": "2017-06-21T05:53:03.102Z", "time": "05:53:03.10", "video_log": "false", "time_in_seconds": "null", "Course_Id": "null", "Kenlist_Id": "null", "offset": 345724575, "date": "2017-06-21"}
{"user_action": "Youtube video is buffering ", "Video_Id": "FLpJ2jLZAYg", "email_id": "6ac533285d26800deb6f3fdb5c1ee6a30807b0433aa3dcd506e9898f", "timestamp": "2017-06-21 05:52:13", "@timestamp": "2017-06-21T05:52:14.079Z", "time": "05:52:14.07", "video_log": "true", "time_in_seconds": "0", "Course_Id": "3136", "Kenlist_Id": "4288", "offset": 345711335, "date": "2017-06-21"}
{"user_action": "User is playing", "Video_Id": "FLpJ2jLZAYg", "email_id": "6ac533285d26800deb6f3fdb5c1ee6a30807b0433aa3dcd506e9898f", "timestamp": "2017-06-21 05:52:13", "@timestamp": "2017-06-21T05:52:14.079Z", "time": "05:52:14.07", "video_log": "true", "time_in_seconds": "0.0009999275207519531", "Course_Id": "3136", "Kenlist_Id": "4288", "offset": 345711815, "date": "2017-06-21"}
{"user_action": "Course details", "Video_Id": "null", "email_id": "6ac533285d26800deb6f3fdb5c1ee6a30807b0433aa3dcd506e9898f", "timestamp": "2017-06-21 05:58:20", "@timestamp": "2017-06-21T05:58:21.178Z", "time": "05:58:21.17", "video_log": "false", "time_in_seconds": "null", "Course_Id": "3136", "Kenlist_Id": "null", "offset": 346109125, "date": "2017-06-21"}
{"user_action": "User start quiz quiz_id : 432", "Video_Id": "null", "email_id": "6ac533285d26800deb6f3fdb5c1ee6a30807b0433aa3dcd506e9898f", "timestamp": "2017-06-21 06:15:47", "@timestamp": "2017-06-21T06:15:47.773Z", "time": "06:15:47.77", "video_log": "false", "time_in_seconds": "null", "Course_Id": "null", "Kenlist_Id": "null", "offset": 347219549, "date": "2017-06-21"}
{"user_action": "On course show page", "Video_Id": "null", "email_id": "6ac533285d26800deb6f3fdb5c1ee6a30807b0433aa3dcd506e9898f", "timestamp": "2017-06-21 06:15:47", "@timestamp": "2017-06-21T06:15:47.773Z", "time": "06:15:47.77", "video_log": "false", "time_in_seconds": "null", "Course_Id": "null", "Kenlist_Id": "null", "offset": 347220864, "date": "2017-06-21"}
{"user_action": "quiz API data received at the front end quiz_id : 432", "Video_Id": "null", "email_id": "6ac533285d26800deb6f3fdb5c1ee6a30807b0433aa3dcd506e9898f", "timestamp": "2017-06-21 06:15:49", "@timestamp": "2017-06-21T06:15:50.771Z", "time": "06:15:50.77", "video_log": "false", "time_in_seconds": "null", "Course_Id": "null", "Kenlist_Id": "null", "offset": 347231186, "date": "2017-06-21"}
{"user_action": "On course show page", "Video_Id": "null", "email_id": "6ac533285d26800deb6f3fdb5c1ee6a30807b0433aa3dcd506e9898f", "timestamp": "2017-06-21 06:46:47", "@timestamp": "2017-06-21T06:46:48.404Z", "time": "06:46:48.40", "video_log": "false", "time_in_seconds": "null", "Course_Id": "null", "Kenlist_Id": "null", "offset": 348785735, "date": "2017-06-21"}
{"user_action": "Discussions of the course", "Video_Id": "null", "email_id": "6ac533285d26800deb6f3fdb5c1ee6a30807b0433aa3dcd506e9898f", "timestamp": "2017-06-21 06:46:47", "@timestamp": "2017-06-21T06:46:48.404Z", "time": "06:46:48.40", "video_log": "false", "time_in_seconds": "null", "Course_Id": "3136", "Kenlist_Id": "null", "offset": 348785944, "date": "2017-06-21"}
